{
  "title": "为什么有的优秀团队很难管理？",
  "date": "2026-06-04 08:30",
  "author_or_account": "刘润公众号公开文章",
  "article_type": "组织管理",
  "topic_tags": [
    "组织管理"
  ],
  "hook_type": "问题式",
  "structure_pattern": "问题-本质-方法式",
  "source_types": [
    "数据/报告",
    "一手观察/咨询场景",
    "商业案例",
    "类比"
  ],
  "word_count_cjk": 6204,
  "images": 17,
  "file": "/Users/lixin/Documents/学习/重点学习公众号/刘润/20260604_为什么有的优秀团队很难管理？.md",
  "notable": "管理，管的不是人，而是人与人之间的信息流和信任流。; “团队就要做大”，可能是上个时代的执念; 很多老板会有一个执念：公司就要越做越大，团队成员就该越来越多。 你问他为什么，他往往会说：招的人才越多，团队越优秀，大团队自然越厉害。 冠宇老师觉得："
}